drf_case_middleware/__init__.py
drf_case_middleware/middlewares.py
drf_case_middleware/parsers.py
drf_case_middleware/renders.py
drf_case_middleware-0.1.2.dist-info/LICENSE
drf_case_middleware-0.1.2.dist-info/METADATA
drf_case_middleware-0.1.2.dist-info/NOTICE
drf_case_middleware-0.1.2.dist-info/WHEEL
drf_case_middleware-0.1.2.dist-info/top_level.txt
drf_case_middleware-0.1.2.dist-info/RECORD
